[
  {
    "Name":"Lee Seung-hyun",
    "League":"KBO",
    "Team":"Samsung",
    "Stat":"Hits Allowed",
    "Versus":"Doosan",
    "Prizepicks":6.5,
    "Odds Type":"demon"
  },
  {
    "Name":"Choi Min-seok",
    "League":"KBO",
    "Team":"Doosan",
    "Stat":"Hits Allowed",
    "Versus":"Samsung",
    "Prizepicks":6.5,
    "Odds Type":"demon"
  },
  {
    "Name":"Choi Min-seok",
    "League":"KBO",
    "Team":"Doosan",
    "Stat":"Pitcher Strikeouts",
    "Versus":"Samsung",
    "Prizepicks":4.5,
    "Odds Type":"demon"
  },
  {
    "Name":"Lee Seung-hyun",
    "League":"KBO",
    "Team":"Samsung",
    "Stat":"Pitcher Strikeouts",
    "Versus":"Doosan",
    "Prizepicks":3.0,
    "Odds Type":"standard"
  },
  {
    "Name":"Lewin D\u00edaz",
    "League":"KBO",
    "Team":"Samsung",
    "Stat":"Hits+Runs+RBIs",
    "Versus":"Doosan",
    "Prizepicks":2.5,
    "Odds Type":"standard"
  },
  {
    "Name":"Koo Ja-wook",
    "League":"KBO",
    "Team":"Samsung",
    "Stat":"Hits+Runs+RBIs",
    "Versus":"Doosan",
    "Prizepicks":2.5,
    "Odds Type":"standard"
  },
  {
    "Name":"Kim Seong-yoon",
    "League":"KBO",
    "Team":"Samsung",
    "Stat":"Hits+Runs+RBIs",
    "Versus":"Doosan",
    "Prizepicks":2.5,
    "Odds Type":"standard"
  },
  {
    "Name":"Choi Hyoung-woo",
    "League":"KBO",
    "Team":"Samsung",
    "Stat":"Hits+Runs+RBIs",
    "Versus":"Doosan",
    "Prizepicks":2.5,
    "Odds Type":"standard"
  },
  {
    "Name":"Park Chan-ho",
    "League":"KBO",
    "Team":"Doosan",
    "Stat":"Hits+Runs+RBIs",
    "Versus":"Samsung",
    "Prizepicks":2.5,
    "Odds Type":"demon"
  },
  {
    "Name":"Daz Cameron",
    "League":"KBO",
    "Team":"Doosan",
    "Stat":"Hits+Runs+RBIs",
    "Versus":"Samsung",
    "Prizepicks":2.5,
    "Odds Type":"demon"
  },
  {
    "Name":"Jung Soo-bin",
    "League":"KBO",
    "Team":"Doosan",
    "Stat":"Hits+Runs+RBIs",
    "Versus":"Samsung",
    "Prizepicks":2.5,
    "Odds Type":"demon"
  },
  {
    "Name":"Yang Eui-ji",
    "League":"KBO",
    "Team":"Doosan",
    "Stat":"Hits+Runs+RBIs",
    "Versus":"Samsung",
    "Prizepicks":2.5,
    "Odds Type":"demon"
  },
  {
    "Name":"Lewin D\u00edaz",
    "League":"KBO",
    "Team":"Samsung",
    "Stat":"Total Bases",
    "Versus":"Doosan",
    "Prizepicks":1.5,
    "Odds Type":"standard"
  },
  {
    "Name":"Oh Won-seok",
    "League":"KBO",
    "Team":"KT",
    "Stat":"Hits Allowed",
    "Versus":"Hanwha",
    "Prizepicks":5.5,
    "Odds Type":"demon"
  },
  {
    "Name":"Oh Won-seok",
    "League":"KBO",
    "Team":"KT",
    "Stat":"Pitcher Strikeouts",
    "Versus":"Hanwha",
    "Prizepicks":5.5,
    "Odds Type":"demon"
  },
  {
    "Name":"Moon Dong-ju",
    "League":"KBO",
    "Team":"Hanwha",
    "Stat":"Hits Allowed",
    "Versus":"KT",
    "Prizepicks":5.5,
    "Odds Type":"demon"
  },
  {
    "Name":"Moon Dong-ju",
    "League":"KBO",
    "Team":"Hanwha",
    "Stat":"Pitcher Strikeouts",
    "Versus":"KT",
    "Prizepicks":3.5,
    "Odds Type":"goblin"
  },
  {
    "Name":"Ahn Hyun-min",
    "League":"KBO",
    "Team":"KT",
    "Stat":"Hits+Runs+RBIs",
    "Versus":"Hanwha",
    "Prizepicks":2.5,
    "Odds Type":"demon"
  },
  {
    "Name":"Sam Hilliard",
    "League":"KBO",
    "Team":"KT",
    "Stat":"Hits+Runs+RBIs",
    "Versus":"Hanwha",
    "Prizepicks":2.5,
    "Odds Type":"demon"
  },
  {
    "Name":"Choi Won-jun",
    "League":"KBO",
    "Team":"KT",
    "Stat":"Hits+Runs+RBIs",
    "Versus":"Hanwha",
    "Prizepicks":2.5,
    "Odds Type":"demon"
  },
  {
    "Name":"Oh Jae-won",
    "League":"KBO",
    "Team":"Hanwha",
    "Stat":"Hits+Runs+RBIs",
    "Versus":"KT",
    "Prizepicks":2.5,
    "Odds Type":"demon"
  },
  {
    "Name":"Roh Si-Hwan",
    "League":"KBO",
    "Team":"Hanwha",
    "Stat":"Hits+Runs+RBIs",
    "Versus":"KT",
    "Prizepicks":2.5,
    "Odds Type":"demon"
  },
  {
    "Name":"Yonathan Perlaza",
    "League":"KBO",
    "Team":"Hanwha",
    "Stat":"Hits+Runs+RBIs",
    "Versus":"KT",
    "Prizepicks":2.5,
    "Odds Type":"demon"
  },
  {
    "Name":"Moon Hyun-bin",
    "League":"KBO",
    "Team":"Hanwha",
    "Stat":"Hits+Runs+RBIs",
    "Versus":"KT",
    "Prizepicks":2.5,
    "Odds Type":"demon"
  },
  {
    "Name":"Park Kun-woo",
    "League":"KBO",
    "Team":"NC",
    "Stat":"Hits+Runs+RBIs",
    "Versus":"Lotte",
    "Prizepicks":2.5,
    "Odds Type":"demon"
  },
  {
    "Name":"Park Min-woo",
    "League":"KBO",
    "Team":"NC",
    "Stat":"Hits+Runs+RBIs",
    "Versus":"Lotte",
    "Prizepicks":2.5,
    "Odds Type":"demon"
  },
  {
    "Name":"Kim Ju-won",
    "League":"KBO",
    "Team":"NC",
    "Stat":"Hits+Runs+RBIs",
    "Versus":"Lotte",
    "Prizepicks":2.5,
    "Odds Type":"demon"
  },
  {
    "Name":"Matthew Davidson",
    "League":"KBO",
    "Team":"NC",
    "Stat":"Hits+Runs+RBIs",
    "Versus":"Lotte",
    "Prizepicks":2.5,
    "Odds Type":"demon"
  },
  {
    "Name":"Jeon Jun-woo",
    "League":"KBO",
    "Team":"Lotte",
    "Stat":"Hits+Runs+RBIs",
    "Versus":"NC",
    "Prizepicks":2.5,
    "Odds Type":"demon"
  },
  {
    "Name":"V\u00edctor Reyes",
    "League":"KBO",
    "Team":"Lotte",
    "Stat":"Hits+Runs+RBIs",
    "Versus":"NC",
    "Prizepicks":2.5,
    "Odds Type":"demon"
  },
  {
    "Name":"Yoon Dong-hee",
    "League":"KBO",
    "Team":"Lotte",
    "Stat":"Hits+Runs+RBIs",
    "Versus":"NC",
    "Prizepicks":2.5,
    "Odds Type":"demon"
  },
  {
    "Name":"Son Ho-young",
    "League":"KBO",
    "Team":"Lotte",
    "Stat":"Hits+Runs+RBIs",
    "Versus":"NC",
    "Prizepicks":2.5,
    "Odds Type":"demon"
  },
  {
    "Name":"Choi Min-jun",
    "League":"KBO",
    "Team":"SSG",
    "Stat":"Hits Allowed",
    "Versus":"Kiwoom",
    "Prizepicks":5.5,
    "Odds Type":"demon"
  },
  {
    "Name":"Choi Min-jun",
    "League":"KBO",
    "Team":"SSG",
    "Stat":"Pitcher Strikeouts",
    "Versus":"Kiwoom",
    "Prizepicks":3.5,
    "Odds Type":"demon"
  },
  {
    "Name":"Guillermo Heredia",
    "League":"KBO",
    "Team":"SSG",
    "Stat":"Hits+Runs+RBIs",
    "Versus":"Kiwoom",
    "Prizepicks":2.5,
    "Odds Type":"standard"
  },
  {
    "Name":"Choi Jeong",
    "League":"KBO",
    "Team":"SSG",
    "Stat":"Hits+Runs+RBIs",
    "Versus":"Kiwoom",
    "Prizepicks":2.5,
    "Odds Type":"standard"
  },
  {
    "Name":"Ko Myeong-jun",
    "League":"KBO",
    "Team":"SSG",
    "Stat":"Hits+Runs+RBIs",
    "Versus":"Kiwoom",
    "Prizepicks":2.5,
    "Odds Type":"demon"
  },
  {
    "Name":"Park Seong-Han",
    "League":"KBO",
    "Team":"SSG",
    "Stat":"Hits+Runs+RBIs",
    "Versus":"Kiwoom",
    "Prizepicks":2.5,
    "Odds Type":"standard"
  },
  {
    "Name":"Lee Ju-hyoung",
    "League":"KBO",
    "Team":"Kiwoom",
    "Stat":"Hits+Runs+RBIs",
    "Versus":"SSG",
    "Prizepicks":2.5,
    "Odds Type":"demon"
  },
  {
    "Name":"Kim Gun-hee",
    "League":"KBO",
    "Team":"Kiwoom",
    "Stat":"Hits+Runs+RBIs",
    "Versus":"SSG",
    "Prizepicks":2.5,
    "Odds Type":"demon"
  },
  {
    "Name":"Trenton Brooks",
    "League":"KBO",
    "Team":"Kiwoom",
    "Stat":"Hits+Runs+RBIs",
    "Versus":"SSG",
    "Prizepicks":2.5,
    "Odds Type":"demon"
  },
  {
    "Name":"An Chi-hong",
    "League":"KBO",
    "Team":"Kiwoom",
    "Stat":"Hits+Runs+RBIs",
    "Versus":"SSG",
    "Prizepicks":2.5,
    "Odds Type":"demon"
  },
  {
    "Name":"Guillermo Heredia",
    "League":"KBO",
    "Team":"SSG",
    "Stat":"Total Bases",
    "Versus":"Kiwoom",
    "Prizepicks":1.5,
    "Odds Type":"standard"
  },
  {
    "Name":"Lachlan Wells",
    "League":"KBO",
    "Team":"LG",
    "Stat":"Hits Allowed",
    "Versus":"Kia",
    "Prizepicks":6.5,
    "Odds Type":"demon"
  },
  {
    "Name":"Kim Tae-hyeong",
    "League":"KBO",
    "Team":"Kia",
    "Stat":"Hits Allowed",
    "Versus":"LG",
    "Prizepicks":6.5,
    "Odds Type":"demon"
  },
  {
    "Name":"Lachlan Wells",
    "League":"KBO",
    "Team":"LG",
    "Stat":"Pitcher Strikeouts",
    "Versus":"Kia",
    "Prizepicks":5.5,
    "Odds Type":"demon"
  },
  {
    "Name":"Kim Tae-hyeong",
    "League":"KBO",
    "Team":"Kia",
    "Stat":"Pitcher Strikeouts",
    "Versus":"LG",
    "Prizepicks":4.5,
    "Odds Type":"demon"
  },
  {
    "Name":"Hong Chang-ki",
    "League":"KBO",
    "Team":"LG",
    "Stat":"Hits+Runs+RBIs",
    "Versus":"Kia",
    "Prizepicks":2.5,
    "Odds Type":"standard"
  },
  {
    "Name":"Moon Bo-gyeong",
    "League":"KBO",
    "Team":"LG",
    "Stat":"Hits+Runs+RBIs",
    "Versus":"Kia",
    "Prizepicks":2.5,
    "Odds Type":"standard"
  },
  {
    "Name":"Austin Dean",
    "League":"KBO",
    "Team":"LG",
    "Stat":"Hits+Runs+RBIs",
    "Versus":"Kia",
    "Prizepicks":2.5,
    "Odds Type":"standard"
  },
  {
    "Name":"Shin Min-jae",
    "League":"KBO",
    "Team":"LG",
    "Stat":"Hits+Runs+RBIs",
    "Versus":"Kia",
    "Prizepicks":2.5,
    "Odds Type":"standard"
  },
  {
    "Name":"Kim Sun-bin",
    "League":"KBO",
    "Team":"Kia",
    "Stat":"Hits+Runs+RBIs",
    "Versus":"LG",
    "Prizepicks":2.5,
    "Odds Type":"demon"
  },
  {
    "Name":"Kim Do-yeong",
    "League":"KBO",
    "Team":"Kia",
    "Stat":"Hits+Runs+RBIs",
    "Versus":"LG",
    "Prizepicks":2.5,
    "Odds Type":"demon"
  },
  {
    "Name":"Na Sung-bum",
    "League":"KBO",
    "Team":"Kia",
    "Stat":"Hits+Runs+RBIs",
    "Versus":"LG",
    "Prizepicks":2.5,
    "Odds Type":"demon"
  },
  {
    "Name":"Harold Castro",
    "League":"KBO",
    "Team":"Kia",
    "Stat":"Hits+Runs+RBIs",
    "Versus":"LG",
    "Prizepicks":2.5,
    "Odds Type":"demon"
  },
  {
    "Name":"Lewin D\u00edaz",
    "League":"KBO",
    "Team":"Samsung",
    "Stat":"Hits+Runs+RBIs",
    "Versus":"Doosan",
    "Prizepicks":1.5,
    "Odds Type":"goblin"
  },
  {
    "Name":"Koo Ja-wook",
    "League":"KBO",
    "Team":"Samsung",
    "Stat":"Hits+Runs+RBIs",
    "Versus":"Doosan",
    "Prizepicks":1.5,
    "Odds Type":"goblin"
  },
  {
    "Name":"Choi Hyoung-woo",
    "League":"KBO",
    "Team":"Samsung",
    "Stat":"Hits+Runs+RBIs",
    "Versus":"Doosan",
    "Prizepicks":1.5,
    "Odds Type":"goblin"
  },
  {
    "Name":"Kim Seong-yoon",
    "League":"KBO",
    "Team":"Samsung",
    "Stat":"Hits+Runs+RBIs",
    "Versus":"Doosan",
    "Prizepicks":1.5,
    "Odds Type":"goblin"
  },
  {
    "Name":"Daz Cameron",
    "League":"KBO",
    "Team":"Doosan",
    "Stat":"Hits+Runs+RBIs",
    "Versus":"Samsung",
    "Prizepicks":1.5,
    "Odds Type":"goblin"
  },
  {
    "Name":"Park Chan-ho",
    "League":"KBO",
    "Team":"Doosan",
    "Stat":"Hits+Runs+RBIs",
    "Versus":"Samsung",
    "Prizepicks":1.5,
    "Odds Type":"goblin"
  },
  {
    "Name":"Jung Soo-bin",
    "League":"KBO",
    "Team":"Doosan",
    "Stat":"Hits+Runs+RBIs",
    "Versus":"Samsung",
    "Prizepicks":1.5,
    "Odds Type":"goblin"
  },
  {
    "Name":"Yang Eui-ji",
    "League":"KBO",
    "Team":"Doosan",
    "Stat":"Hits+Runs+RBIs",
    "Versus":"Samsung",
    "Prizepicks":1.5,
    "Odds Type":"goblin"
  },
  {
    "Name":"Yonathan Perlaza",
    "League":"KBO",
    "Team":"Hanwha",
    "Stat":"Hits+Runs+RBIs",
    "Versus":"KT",
    "Prizepicks":1.5,
    "Odds Type":"standard"
  },
  {
    "Name":"Oh Jae-won",
    "League":"KBO",
    "Team":"Hanwha",
    "Stat":"Hits+Runs+RBIs",
    "Versus":"KT",
    "Prizepicks":1.5,
    "Odds Type":"standard"
  },
  {
    "Name":"Moon Hyun-bin",
    "League":"KBO",
    "Team":"Hanwha",
    "Stat":"Hits+Runs+RBIs",
    "Versus":"KT",
    "Prizepicks":1.5,
    "Odds Type":"standard"
  },
  {
    "Name":"Roh Si-Hwan",
    "League":"KBO",
    "Team":"Hanwha",
    "Stat":"Hits+Runs+RBIs",
    "Versus":"KT",
    "Prizepicks":1.5,
    "Odds Type":"demon"
  },
  {
    "Name":"Sam Hilliard",
    "League":"KBO",
    "Team":"KT",
    "Stat":"Hits+Runs+RBIs",
    "Versus":"Hanwha",
    "Prizepicks":1.5,
    "Odds Type":"standard"
  },
  {
    "Name":"Ahn Hyun-min",
    "League":"KBO",
    "Team":"KT",
    "Stat":"Hits+Runs+RBIs",
    "Versus":"Hanwha",
    "Prizepicks":1.5,
    "Odds Type":"goblin"
  },
  {
    "Name":"Choi Won-jun",
    "League":"KBO",
    "Team":"KT",
    "Stat":"Hits+Runs+RBIs",
    "Versus":"Hanwha",
    "Prizepicks":1.5,
    "Odds Type":"standard"
  },
  {
    "Name":"Matthew Davidson",
    "League":"KBO",
    "Team":"NC",
    "Stat":"Hits+Runs+RBIs",
    "Versus":"Lotte",
    "Prizepicks":1.5,
    "Odds Type":"goblin"
  },
  {
    "Name":"Kim Ju-won",
    "League":"KBO",
    "Team":"NC",
    "Stat":"Hits+Runs+RBIs",
    "Versus":"Lotte",
    "Prizepicks":1.5,
    "Odds Type":"goblin"
  },
  {
    "Name":"Park Min-woo",
    "League":"KBO",
    "Team":"NC",
    "Stat":"Hits+Runs+RBIs",
    "Versus":"Lotte",
    "Prizepicks":1.5,
    "Odds Type":"goblin"
  },
  {
    "Name":"Park Kun-woo",
    "League":"KBO",
    "Team":"NC",
    "Stat":"Hits+Runs+RBIs",
    "Versus":"Lotte",
    "Prizepicks":1.5,
    "Odds Type":"goblin"
  },
  {
    "Name":"V\u00edctor Reyes",
    "League":"KBO",
    "Team":"Lotte",
    "Stat":"Hits+Runs+RBIs",
    "Versus":"NC",
    "Prizepicks":1.5,
    "Odds Type":"goblin"
  },
  {
    "Name":"Yoon Dong-hee",
    "League":"KBO",
    "Team":"Lotte",
    "Stat":"Hits+Runs+RBIs",
    "Versus":"NC",
    "Prizepicks":1.5,
    "Odds Type":"goblin"
  },
  {
    "Name":"Jeon Jun-woo",
    "League":"KBO",
    "Team":"Lotte",
    "Stat":"Hits+Runs+RBIs",
    "Versus":"NC",
    "Prizepicks":1.5,
    "Odds Type":"goblin"
  },
  {
    "Name":"Son Ho-young",
    "League":"KBO",
    "Team":"Lotte",
    "Stat":"Hits+Runs+RBIs",
    "Versus":"NC",
    "Prizepicks":1.5,
    "Odds Type":"goblin"
  },
  {
    "Name":"Guillermo Heredia",
    "League":"KBO",
    "Team":"SSG",
    "Stat":"Hits+Runs+RBIs",
    "Versus":"Kiwoom",
    "Prizepicks":1.5,
    "Odds Type":"goblin"
  },
  {
    "Name":"Choi Jeong",
    "League":"KBO",
    "Team":"SSG",
    "Stat":"Hits+Runs+RBIs",
    "Versus":"Kiwoom",
    "Prizepicks":1.5,
    "Odds Type":"goblin"
  },
  {
    "Name":"Park Seong-Han",
    "League":"KBO",
    "Team":"SSG",
    "Stat":"Hits+Runs+RBIs",
    "Versus":"Kiwoom",
    "Prizepicks":1.5,
    "Odds Type":"goblin"
  },
  {
    "Name":"Ko Myeong-jun",
    "League":"KBO",
    "Team":"SSG",
    "Stat":"Hits+Runs+RBIs",
    "Versus":"Kiwoom",
    "Prizepicks":1.5,
    "Odds Type":"goblin"
  },
  {
    "Name":"Trenton Brooks",
    "League":"KBO",
    "Team":"Kiwoom",
    "Stat":"Hits+Runs+RBIs",
    "Versus":"SSG",
    "Prizepicks":1.5,
    "Odds Type":"goblin"
  },
  {
    "Name":"An Chi-hong",
    "League":"KBO",
    "Team":"Kiwoom",
    "Stat":"Hits+Runs+RBIs",
    "Versus":"SSG",
    "Prizepicks":1.5,
    "Odds Type":"goblin"
  },
  {
    "Name":"Lee Ju-hyoung",
    "League":"KBO",
    "Team":"Kiwoom",
    "Stat":"Hits+Runs+RBIs",
    "Versus":"SSG",
    "Prizepicks":1.5,
    "Odds Type":"standard"
  },
  {
    "Name":"Kim Gun-hee",
    "League":"KBO",
    "Team":"Kiwoom",
    "Stat":"Hits+Runs+RBIs",
    "Versus":"SSG",
    "Prizepicks":1.5,
    "Odds Type":"standard"
  },
  {
    "Name":"Austin Dean",
    "League":"KBO",
    "Team":"LG",
    "Stat":"Hits+Runs+RBIs",
    "Versus":"Kia",
    "Prizepicks":1.5,
    "Odds Type":"goblin"
  },
  {
    "Name":"Hong Chang-ki",
    "League":"KBO",
    "Team":"LG",
    "Stat":"Hits+Runs+RBIs",
    "Versus":"Kia",
    "Prizepicks":1.5,
    "Odds Type":"goblin"
  },
  {
    "Name":"Moon Bo-gyeong",
    "League":"KBO",
    "Team":"LG",
    "Stat":"Hits+Runs+RBIs",
    "Versus":"Kia",
    "Prizepicks":1.5,
    "Odds Type":"goblin"
  },
  {
    "Name":"Shin Min-jae",
    "League":"KBO",
    "Team":"LG",
    "Stat":"Hits+Runs+RBIs",
    "Versus":"Kia",
    "Prizepicks":1.5,
    "Odds Type":"goblin"
  },
  {
    "Name":"Harold Castro",
    "League":"KBO",
    "Team":"Kia",
    "Stat":"Hits+Runs+RBIs",
    "Versus":"LG",
    "Prizepicks":1.5,
    "Odds Type":"standard"
  },
  {
    "Name":"Kim Do-yeong",
    "League":"KBO",
    "Team":"Kia",
    "Stat":"Hits+Runs+RBIs",
    "Versus":"LG",
    "Prizepicks":1.5,
    "Odds Type":"standard"
  },
  {
    "Name":"Na Sung-bum",
    "League":"KBO",
    "Team":"Kia",
    "Stat":"Hits+Runs+RBIs",
    "Versus":"LG",
    "Prizepicks":1.5,
    "Odds Type":"standard"
  },
  {
    "Name":"Kim Sun-bin",
    "League":"KBO",
    "Team":"Kia",
    "Stat":"Hits+Runs+RBIs",
    "Versus":"LG",
    "Prizepicks":1.5,
    "Odds Type":"standard"
  },
  {
    "Name":"Lee Seung-hyun",
    "League":"KBO",
    "Team":"Samsung",
    "Stat":"Pitcher Strikeouts",
    "Versus":"Doosan",
    "Prizepicks":4.5,
    "Odds Type":"demon"
  },
  {
    "Name":"Choi Min-seok",
    "League":"KBO",
    "Team":"Doosan",
    "Stat":"Pitcher Strikeouts",
    "Versus":"Samsung",
    "Prizepicks":2.5,
    "Odds Type":"standard"
  },
  {
    "Name":"Moon Dong-ju",
    "League":"KBO",
    "Team":"Hanwha",
    "Stat":"Pitcher Strikeouts",
    "Versus":"KT",
    "Prizepicks":4.5,
    "Odds Type":"demon"
  },
  {
    "Name":"Oh Won-seok",
    "League":"KBO",
    "Team":"KT",
    "Stat":"Pitcher Strikeouts",
    "Versus":"Hanwha",
    "Prizepicks":4.0,
    "Odds Type":"standard"
  },
  {
    "Name":"Jung Hyun-woo",
    "League":"KBO",
    "Team":"Kiwoom",
    "Stat":"Pitcher Strikeouts",
    "Versus":"SSG",
    "Prizepicks":3.5,
    "Odds Type":"goblin"
  },
  {
    "Name":"Choi Min-jun",
    "League":"KBO",
    "Team":"SSG",
    "Stat":"Pitcher Strikeouts",
    "Versus":"Kiwoom",
    "Prizepicks":2.5,
    "Odds Type":"goblin"
  },
  {
    "Name":"Lachlan Wells",
    "League":"KBO",
    "Team":"LG",
    "Stat":"Pitcher Strikeouts",
    "Versus":"Kia",
    "Prizepicks":3.5,
    "Odds Type":"standard"
  },
  {
    "Name":"Kim Tae-hyeong",
    "League":"KBO",
    "Team":"Kia",
    "Stat":"Pitcher Strikeouts",
    "Versus":"LG",
    "Prizepicks":2.5,
    "Odds Type":"standard"
  }
]