{
  "generated_at": "2026-06-01T18:16:12.650217+00:00",
  "projections": [
    {
      "name": "Wesley Benjamin",
      "team": "Doosan",
      "opponent": "Hanwha",
      "line": 4.5,
      "odds_type": "standard",
      "pp_name": "Wesley Benjamin",
      "prop": "Strikeouts",
      "prop_key": "strikeouts",
      "projection": 4.09,
      "edge": -0.41,
      "rating": 45.5,
      "recommendation": "PUSH",
      "so_per_ip": 0.873,
      "ip_per_g": 4.654,
      "opp_so_per_g": 7.65,
      "league_avg_so_per_g": 7.513,
      "games_used": 0,
      "whip": null,
      "opp_factor": 1.006,
      "whip_factor": 1.0,
      "form_factor": 1.0,
      "hit_rate_l5": null,
      "hit_rate_full": null,
      "recent_values": [],
      "source": "fallback_prior_line_or_league"
    },
    {
      "name": "Wesley Benjamin",
      "team": "Doosan",
      "opponent": "Hanwha",
      "line": 5.5,
      "odds_type": "standard",
      "pp_name": "Wesley Benjamin",
      "prop": "Hits Allowed",
      "prop_key": "hits_allowed",
      "projection": 4.7,
      "edge": -0.8,
      "rating": 42.8,
      "recommendation": "UNDER",
      "hits_per_ip": 0.969,
      "ip_per_g": 4.654,
      "opp_h_per_ip": 1.12,
      "league_avg_h_per_ip": 1.01,
      "games_used": 0,
      "whip": null,
      "opp_factor": 1.043,
      "whip_factor": 1.0,
      "form_factor": 1.0,
      "hit_rate_l5": null,
      "hit_rate_full": null,
      "recent_values": [],
      "source": "fallback_prior_line_or_league"
    },
    {
      "name": "Wesley Benjamin",
      "team": "Doosan",
      "opponent": "Hanwha",
      "line": 17.5,
      "odds_type": "goblin",
      "pp_name": "Wesley Benjamin",
      "prop": "Pitching Outs",
      "prop_key": "pitching_outs",
      "projection": 13.58,
      "edge": -3.92,
      "rating": 38.8,
      "recommendation": "PUSH",
      "ip_per_g": 4.654,
      "opp_so_per_g": 7.65,
      "opp_h_per_ip": 1.12,
      "league_avg_so_per_g": 7.513,
      "league_avg_h_per_ip": 1.01,
      "games_used": 0,
      "whip": null,
      "opp_factor": 0.973,
      "whip_factor": 1.0,
      "form_factor": 1.0,
      "hit_rate_l5": null,
      "hit_rate_full": null,
      "recent_values": [],
      "source": "fallback_prior_line_or_league"
    },
    {
      "name": "Natsuki Toda",
      "team": "NC",
      "opponent": "Samsung",
      "line": 4.0,
      "odds_type": "standard",
      "pp_name": "Natsuki Toda",
      "prop": "Strikeouts",
      "prop_key": "strikeouts",
      "projection": 4.49,
      "edge": 0.49,
      "rating": 56.2,
      "recommendation": "OVER",
      "so_per_ip": 0.776,
      "ip_per_g": 5.456,
      "opp_so_per_g": 6.83,
      "league_avg_so_per_g": 7.513,
      "games_used": 10,
      "whip": 1.448,
      "opp_factor": 0.968,
      "whip_factor": 1.0,
      "form_factor": 1.097,
      "hit_rate_l5": 60.0,
      "hit_rate_full": 40.0,
      "recent_values": [
        4.0,
        5.0,
        5.0,
        5.0,
        4.0,
        2.0,
        5.0,
        2.0,
        2.0,
        4.0
      ],
      "source": "weighted_logs"
    },
    {
      "name": "Natsuki Toda",
      "team": "NC",
      "opponent": "Samsung",
      "line": 5.5,
      "odds_type": "standard",
      "pp_name": "Natsuki Toda",
      "prop": "Hits Allowed",
      "prop_key": "hits_allowed",
      "projection": 6.32,
      "edge": 0.82,
      "rating": 57.4,
      "recommendation": "OVER",
      "hits_per_ip": 1.13,
      "ip_per_g": 5.456,
      "opp_h_per_ip": 1.075,
      "league_avg_h_per_ip": 1.01,
      "games_used": 10,
      "whip": 1.448,
      "opp_factor": 1.026,
      "whip_factor": 1.0,
      "form_factor": 1.0,
      "hit_rate_l5": 60.0,
      "hit_rate_full": 50.0,
      "recent_values": [
        7.0,
        8.0,
        8.0,
        4.0,
        5.0,
        8.0,
        5.0,
        4.0,
        6.0,
        3.0
      ],
      "source": "weighted_logs"
    },
    {
      "name": "Natsuki Toda",
      "team": "NC",
      "opponent": "Samsung",
      "line": 17.5,
      "odds_type": "goblin",
      "pp_name": "Natsuki Toda",
      "prop": "Pitching Outs",
      "prop_key": "pitching_outs",
      "projection": 17.72,
      "edge": 0.22,
      "rating": 50.6,
      "recommendation": "PUSH",
      "ip_per_g": 5.456,
      "opp_so_per_g": 6.83,
      "opp_h_per_ip": 1.075,
      "league_avg_so_per_g": 7.513,
      "league_avg_h_per_ip": 1.01,
      "games_used": 10,
      "whip": 1.448,
      "opp_factor": 0.984,
      "whip_factor": 1.0,
      "form_factor": 1.1,
      "hit_rate_l5": 40.0,
      "hit_rate_full": 40.0,
      "recent_values": [
        18,
        17,
        17,
        18,
        15,
        18,
        12,
        6,
        18,
        15
      ],
      "source": "weighted_logs"
    },
    {
      "name": "Ariel Jurado",
      "team": "Samsung",
      "opponent": "NC",
      "line": 5.0,
      "odds_type": "standard",
      "pp_name": "Ariel Jurado",
      "prop": "Strikeouts",
      "prop_key": "strikeouts",
      "projection": 5.21,
      "edge": 0.21,
      "rating": 52.1,
      "recommendation": "PUSH",
      "so_per_ip": 0.756,
      "ip_per_g": 6.298,
      "opp_so_per_g": 7.42,
      "league_avg_so_per_g": 7.513,
      "games_used": 12,
      "whip": 1.306,
      "opp_factor": 0.996,
      "whip_factor": 1.0,
      "form_factor": 1.1,
      "hit_rate_l5": 20.0,
      "hit_rate_full": 16.7,
      "recent_values": [
        3.0,
        5.0,
        5.0,
        7.0,
        5.0,
        2.0,
        7.0,
        5.0,
        5.0,
        4.0
      ],
      "source": "weighted_logs"
    },
    {
      "name": "Ariel Jurado",
      "team": "Samsung",
      "opponent": "NC",
      "line": 5.5,
      "odds_type": "standard",
      "pp_name": "Ariel Jurado",
      "prop": "Hits Allowed",
      "prop_key": "hits_allowed",
      "projection": 7.15,
      "edge": 1.65,
      "rating": 65.0,
      "recommendation": "OVER",
      "hits_per_ip": 1.036,
      "ip_per_g": 6.298,
      "opp_h_per_ip": 1.0,
      "league_avg_h_per_ip": 1.01,
      "games_used": 12,
      "whip": 1.306,
      "opp_factor": 0.996,
      "whip_factor": 1.0,
      "form_factor": 1.1,
      "hit_rate_l5": 60.0,
      "hit_rate_full": 58.3,
      "recent_values": [
        5.0,
        8.0,
        8.0,
        10.0,
        5.0,
        5.0,
        6.0,
        4.0,
        6.0,
        6.0
      ],
      "source": "weighted_logs"
    },
    {
      "name": "Ariel Jurado",
      "team": "Samsung",
      "opponent": "NC",
      "line": 17.5,
      "odds_type": "goblin",
      "pp_name": "Ariel Jurado",
      "prop": "Pitching Outs",
      "prop_key": "pitching_outs",
      "projection": 18.2,
      "edge": 0.7,
      "rating": 52.0,
      "recommendation": "PUSH",
      "ip_per_g": 6.298,
      "opp_so_per_g": 7.42,
      "opp_h_per_ip": 1.0,
      "league_avg_so_per_g": 7.513,
      "league_avg_h_per_ip": 1.01,
      "games_used": 12,
      "whip": 1.306,
      "opp_factor": 1.003,
      "whip_factor": 1.0,
      "form_factor": 0.961,
      "hit_rate_l5": 60.0,
      "hit_rate_full": 83.3,
      "recent_values": [
        21,
        17,
        17,
        21,
        18,
        18,
        21,
        21,
        21,
        18
      ],
      "source": "weighted_logs"
    },
    {
      "name": "Raul Alcantara",
      "team": "Kiwoom",
      "opponent": "SSG",
      "line": 5.5,
      "odds_type": "standard",
      "pp_name": "Raul Alcantara",
      "prop": "Strikeouts",
      "prop_key": "strikeouts",
      "projection": 6.11,
      "edge": 0.61,
      "rating": 55.6,
      "recommendation": "OVER",
      "so_per_ip": 0.916,
      "ip_per_g": 6.991,
      "opp_so_per_g": 7.45,
      "league_avg_so_per_g": 7.513,
      "games_used": 13,
      "whip": 1.036,
      "opp_factor": 0.997,
      "whip_factor": 1.0,
      "form_factor": 0.957,
      "hit_rate_l5": 80.0,
      "hit_rate_full": 61.5,
      "recent_values": [
        8.0,
        8.0,
        8.0,
        6.0,
        2.0,
        3.0,
        5.0,
        6.0,
        11.0,
        7.0
      ],
      "source": "weighted_logs"
    },
    {
      "name": "Raul Alcantara",
      "team": "Kiwoom",
      "opponent": "SSG",
      "line": 5.5,
      "odds_type": "standard",
      "pp_name": "Raul Alcantara",
      "prop": "Hits Allowed",
      "prop_key": "hits_allowed",
      "projection": 5.49,
      "edge": -0.01,
      "rating": 49.9,
      "recommendation": "PUSH",
      "hits_per_ip": 0.882,
      "ip_per_g": 6.991,
      "opp_h_per_ip": 0.981,
      "league_avg_h_per_ip": 1.01,
      "games_used": 13,
      "whip": 1.036,
      "opp_factor": 0.988,
      "whip_factor": 1.0,
      "form_factor": 0.9,
      "hit_rate_l5": 20.0,
      "hit_rate_full": 69.2,
      "recent_values": [
        5.0,
        5.0,
        2.0,
        4.0,
        9.0,
        10.0,
        7.0,
        7.0,
        10.0,
        6.0
      ],
      "source": "weighted_logs"
    },
    {
      "name": "Raul Alcantara",
      "team": "Kiwoom",
      "opponent": "SSG",
      "line": 18.5,
      "odds_type": "demon",
      "pp_name": "Raul Alcantara",
      "prop": "Pitching Outs",
      "prop_key": "pitching_outs",
      "projection": 23.24,
      "edge": 4.74,
      "rating": 62.8,
      "recommendation": "OVER",
      "ip_per_g": 6.991,
      "opp_so_per_g": 7.45,
      "opp_h_per_ip": 0.981,
      "league_avg_so_per_g": 7.513,
      "league_avg_h_per_ip": 1.01,
      "games_used": 13,
      "whip": 1.036,
      "opp_factor": 1.007,
      "whip_factor": 1.0,
      "form_factor": 1.1,
      "hit_rate_l5": 80.0,
      "hit_rate_full": 53.8,
      "recent_values": [
        22,
        22,
        24,
        21,
        15,
        18,
        24,
        18,
        18,
        19
      ],
      "source": "weighted_logs"
    },
    {
      "name": "Anthony Veneziano",
      "team": "SSG",
      "opponent": "Kiwoom",
      "line": 4.0,
      "odds_type": "standard",
      "pp_name": "Anthony Veneziano",
      "prop": "Strikeouts",
      "prop_key": "strikeouts",
      "projection": 3.37,
      "edge": -0.63,
      "rating": 42.1,
      "recommendation": "UNDER",
      "so_per_ip": 0.707,
      "ip_per_g": 4.729,
      "opp_so_per_g": 8.58,
      "league_avg_so_per_g": 7.513,
      "games_used": 17,
      "whip": 2.207,
      "opp_factor": 1.05,
      "whip_factor": 1.0,
      "form_factor": 0.96,
      "hit_rate_l5": 40.0,
      "hit_rate_full": 29.4,
      "recent_values": [
        2.0,
        2.0,
        5.0,
        5.0,
        1.0,
        1.0,
        7.0,
        7.0,
        3.0,
        5.0
      ],
      "source": "weighted_logs"
    },
    {
      "name": "Anthony Veneziano",
      "team": "SSG",
      "opponent": "Kiwoom",
      "line": 5.5,
      "odds_type": "standard",
      "pp_name": "Anthony Veneziano",
      "prop": "Hits Allowed",
      "prop_key": "hits_allowed",
      "projection": 5.19,
      "edge": -0.31,
      "rating": 47.1,
      "recommendation": "PUSH",
      "hits_per_ip": 1.237,
      "ip_per_g": 4.729,
      "opp_h_per_ip": 0.863,
      "league_avg_h_per_ip": 1.01,
      "games_used": 17,
      "whip": 2.207,
      "opp_factor": 0.942,
      "whip_factor": 1.0,
      "form_factor": 0.941,
      "hit_rate_l5": 40.0,
      "hit_rate_full": 58.8,
      "recent_values": [
        6.0,
        6.0,
        5.0,
        5.0,
        4.0,
        4.0,
        6.0,
        6.0,
        3.0,
        6.0
      ],
      "source": "weighted_logs"
    },
    {
      "name": "Anthony Veneziano",
      "team": "SSG",
      "opponent": "Kiwoom",
      "line": 15.5,
      "odds_type": "standard",
      "pp_name": "Anthony Veneziano",
      "prop": "Pitching Outs",
      "prop_key": "pitching_outs",
      "projection": 15.74,
      "edge": 0.24,
      "rating": 50.8,
      "recommendation": "PUSH",
      "ip_per_g": 4.729,
      "opp_so_per_g": 8.58,
      "opp_h_per_ip": 0.863,
      "league_avg_so_per_g": 7.513,
      "league_avg_h_per_ip": 1.01,
      "games_used": 17,
      "whip": 2.207,
      "opp_factor": 1.036,
      "whip_factor": 1.0,
      "form_factor": 1.07,
      "hit_rate_l5": 40.0,
      "hit_rate_full": 35.3,
      "recent_values": [
        14,
        14,
        16,
        16,
        5,
        5,
        17,
        17,
        15,
        15
      ],
      "source": "weighted_logs"
    },
    {
      "name": "Na Gyun An",
      "team": "Lotte",
      "opponent": "Kia",
      "line": 4.5,
      "odds_type": "standard",
      "pp_name": "Na Gyun-an",
      "prop": "Strikeouts",
      "prop_key": "strikeouts",
      "projection": 6.26,
      "edge": 1.76,
      "rating": 69.5,
      "recommendation": "OVER",
      "so_per_ip": 0.984,
      "ip_per_g": 5.763,
      "opp_so_per_g": 7.57,
      "league_avg_so_per_g": 7.513,
      "games_used": 15,
      "whip": 1.575,
      "opp_factor": 1.003,
      "whip_factor": 1.0,
      "form_factor": 1.1,
      "hit_rate_l5": 100.0,
      "hit_rate_full": 60.0,
      "recent_values": [
        7.0,
        7.0,
        6.0,
        6.0,
        6.0,
        6.0,
        2.0,
        2.0,
        7.0,
        4.0
      ],
      "source": "weighted_logs"
    },
    {
      "name": "Na Gyun An",
      "team": "Lotte",
      "opponent": "Kia",
      "line": 5.5,
      "odds_type": "standard",
      "pp_name": "Na Gyun-an",
      "prop": "Hits Allowed",
      "prop_key": "hits_allowed",
      "projection": 7.41,
      "edge": 1.91,
      "rating": 67.3,
      "recommendation": "OVER",
      "hits_per_ip": 1.173,
      "ip_per_g": 5.763,
      "opp_h_per_ip": 1.0,
      "league_avg_h_per_ip": 1.01,
      "games_used": 15,
      "whip": 1.575,
      "opp_factor": 0.996,
      "whip_factor": 1.0,
      "form_factor": 1.1,
      "hit_rate_l5": 60.0,
      "hit_rate_full": 66.7,
      "recent_values": [
        9.0,
        9.0,
        5.0,
        5.0,
        7.0,
        7.0,
        9.0,
        9.0,
        6.0,
        3.0
      ],
      "source": "weighted_logs"
    },
    {
      "name": "Na Gyun An",
      "team": "Lotte",
      "opponent": "Kia",
      "line": 17.5,
      "odds_type": "goblin",
      "pp_name": "Na Gyun-an",
      "prop": "Pitching Outs",
      "prop_key": "pitching_outs",
      "projection": 18.21,
      "edge": 0.71,
      "rating": 52.0,
      "recommendation": "PUSH",
      "ip_per_g": 5.763,
      "opp_so_per_g": 7.57,
      "opp_h_per_ip": 1.0,
      "league_avg_so_per_g": 7.513,
      "league_avg_h_per_ip": 1.01,
      "games_used": 15,
      "whip": 1.575,
      "opp_factor": 1.003,
      "whip_factor": 1.0,
      "form_factor": 1.05,
      "hit_rate_l5": 40.0,
      "hit_rate_full": 46.7,
      "recent_values": [
        19,
        19,
        16,
        16,
        14,
        14,
        19,
        19,
        21,
        18
      ],
      "source": "weighted_logs"
    },
    {
      "name": "James Naile",
      "team": "Kia",
      "opponent": "Lotte",
      "line": 4.5,
      "odds_type": "standard",
      "pp_name": "James Naile",
      "prop": "Strikeouts",
      "prop_key": "strikeouts",
      "projection": 4.78,
      "edge": 0.28,
      "rating": 53.1,
      "recommendation": "PUSH",
      "so_per_ip": 0.786,
      "ip_per_g": 5.847,
      "opp_so_per_g": 7.83,
      "league_avg_so_per_g": 7.513,
      "games_used": 12,
      "whip": 1.129,
      "opp_factor": 1.015,
      "whip_factor": 1.0,
      "form_factor": 1.024,
      "hit_rate_l5": 20.0,
      "hit_rate_full": 25.0,
      "recent_values": [
        8.0,
        4.0,
        4.0,
        3.0,
        4.0,
        4.0,
        4.0,
        4.0,
        3.0,
        4.0
      ],
      "source": "weighted_logs"
    },
    {
      "name": "James Naile",
      "team": "Kia",
      "opponent": "Lotte",
      "line": 5.5,
      "odds_type": "standard",
      "pp_name": "James Naile",
      "prop": "Hits Allowed",
      "prop_key": "hits_allowed",
      "projection": 5.34,
      "edge": -0.16,
      "rating": 48.5,
      "recommendation": "PUSH",
      "hits_per_ip": 0.934,
      "ip_per_g": 5.847,
      "opp_h_per_ip": 1.0,
      "league_avg_h_per_ip": 1.01,
      "games_used": 12,
      "whip": 1.129,
      "opp_factor": 0.996,
      "whip_factor": 1.0,
      "form_factor": 0.982,
      "hit_rate_l5": 60.0,
      "hit_rate_full": 66.7,
      "recent_values": [
        6.0,
        6.0,
        6.0,
        5.0,
        5.0,
        7.0,
        8.0,
        6.0,
        6.0,
        6.0
      ],
      "source": "weighted_logs"
    },
    {
      "name": "James Naile",
      "team": "Kia",
      "opponent": "Lotte",
      "line": 17.5,
      "odds_type": "goblin",
      "pp_name": "James Naile",
      "prop": "Pitching Outs",
      "prop_key": "pitching_outs",
      "projection": 18.1,
      "edge": 0.6,
      "rating": 51.7,
      "recommendation": "PUSH",
      "ip_per_g": 5.847,
      "opp_so_per_g": 7.83,
      "opp_h_per_ip": 1.0,
      "league_avg_so_per_g": 7.513,
      "league_avg_h_per_ip": 1.01,
      "games_used": 12,
      "whip": 1.129,
      "opp_factor": 1.003,
      "whip_factor": 1.0,
      "form_factor": 1.029,
      "hit_rate_l5": 60.0,
      "hit_rate_full": 50.0,
      "recent_values": [
        21,
        16,
        16,
        18,
        18,
        15,
        18,
        15,
        15,
        21
      ],
      "source": "weighted_logs"
    },
    {
      "name": "Im Chan Kyu",
      "team": "LG",
      "opponent": "KT",
      "line": 3.5,
      "odds_type": "standard",
      "pp_name": "Im Chan-Kyu",
      "prop": "Strikeouts",
      "prop_key": "strikeouts",
      "projection": 3.31,
      "edge": -0.19,
      "rating": 47.2,
      "recommendation": "PUSH",
      "so_per_ip": 0.558,
      "ip_per_g": 5.726,
      "opp_so_per_g": 7.58,
      "league_avg_so_per_g": 7.513,
      "games_used": 14,
      "whip": 1.387,
      "opp_factor": 1.003,
      "whip_factor": 1.0,
      "form_factor": 1.032,
      "hit_rate_l5": 40.0,
      "hit_rate_full": 28.6,
      "recent_values": [
        4.0,
        3.0,
        2.0,
        2.0,
        5.0,
        4.0,
        4.0,
        2.0,
        2.0,
        3.0
      ],
      "source": "weighted_logs"
    },
    {
      "name": "Im Chan Kyu",
      "team": "LG",
      "opponent": "KT",
      "line": 6.5,
      "odds_type": "demon",
      "pp_name": "Im Chan-Kyu",
      "prop": "Hits Allowed",
      "prop_key": "hits_allowed",
      "projection": 5.97,
      "edge": -0.53,
      "rating": 45.9,
      "recommendation": "PUSH",
      "hits_per_ip": 1.109,
      "ip_per_g": 5.726,
      "opp_h_per_ip": 1.122,
      "league_avg_h_per_ip": 1.01,
      "games_used": 14,
      "whip": 1.387,
      "opp_factor": 1.044,
      "whip_factor": 1.0,
      "form_factor": 0.9,
      "hit_rate_l5": 0.0,
      "hit_rate_full": 28.6,
      "recent_values": [
        6.0,
        6.0,
        6.0,
        6.0,
        6.0,
        6.0,
        6.0,
        6.0,
        6.0,
        9.0
      ],
      "source": "weighted_logs"
    },
    {
      "name": "Im Chan Kyu",
      "team": "LG",
      "opponent": "KT",
      "line": null,
      "odds_type": null,
      "pp_name": null,
      "prop": "Pitching Outs",
      "prop_key": "pitching_outs",
      "projection": 18.2,
      "edge": null,
      "rating": null,
      "recommendation": "NO LINE",
      "ip_per_g": 5.726,
      "opp_so_per_g": 7.58,
      "opp_h_per_ip": 1.122,
      "league_avg_so_per_g": 7.513,
      "league_avg_h_per_ip": 1.01,
      "games_used": 14,
      "whip": 1.387,
      "opp_factor": 0.972,
      "whip_factor": 1.0,
      "form_factor": 1.09,
      "hit_rate_l5": null,
      "hit_rate_full": null,
      "recent_values": [],
      "source": "weighted_logs"
    }
  ],
  "league_avg_so_per_g": 7.513,
  "league_avg_h_per_ip": 1.01,
  "team_so_per_g": {
    "Hanwha": 7.65,
    "KT": 7.58,
    "Samsung": 6.83,
    "Kia": 7.57,
    "SSG": 7.45,
    "NC": 7.42,
    "Doosan": 7.07,
    "LG": 7.15,
    "Lotte": 7.83,
    "Kiwoom": 8.58
  },
  "team_h_per_ip": {
    "Hanwha": 1.12,
    "KT": 1.122,
    "Samsung": 1.075,
    "Kia": 1.0,
    "SSG": 0.981,
    "NC": 1.0,
    "Doosan": 0.975,
    "LG": 0.969,
    "Lotte": 1.0,
    "Kiwoom": 0.863
  },
  "models": {
    "strikeouts": "weighted_soip_ipg_with_opp_whip_form",
    "hits_allowed": "weighted_hip_ipg_with_opp_hitrate_whip_form",
    "pitching_outs": "ipg_times_three_with_opp_context_whip_form"
  }
}